{
  "id": 4870565,
  "name": "Elijah Saunders",
  "team": "MD",
  "teamName": "Maryland Terrapins",
  "conference": "Big Ten",
  "rank": 342,
  "gp": 26,
  "ppg": 8.6,
  "adjPpg": 8.9,
  "pointsPlus": 92,
  "mpg": 29.3,
  "position": "F",
  "jersey": "13",
  "classYear": "Senior",
  "pointsPlusStdDev": 57.1,
  "volatilityPctile": 62,
  "gameLog": [
    {
      "date": "2025-11-03",
      "matchup": "MD vs COPP",
      "result": "W",
      "min": 28,
      "pts": 14,
      "adjPts": 14.0,
      "pointsPlus": 146
    },
    {
      "date": "2025-11-07",
      "matchup": "MD vs GTWN",
      "result": "L",
      "min": 26,
      "pts": 5,
      "adjPts": 5.1,
      "pointsPlus": 53
    },
    {
      "date": "2025-11-11",
      "matchup": "MD vs ALCN",
      "result": "W",
      "min": 26,
      "pts": 12,
      "adjPts": 12.0,
      "pointsPlus": 125
    },
    {
      "date": "2025-11-15",
      "matchup": "MD @ MARQ",
      "result": "W",
      "min": 38,
      "pts": 8,
      "adjPts": 7.5,
      "pointsPlus": 78
    },
    {
      "date": "2025-11-19",
      "matchup": "MD vs MSM",
      "result": "W",
      "min": 44,
      "pts": 14,
      "adjPts": 14.0,
      "pointsPlus": 146
    },
    {
      "date": "2025-11-24",
      "matchup": "MD vs UNLV",
      "result": "W",
      "min": 27,
      "pts": 2,
      "adjPts": 2.0,
      "pointsPlus": 21
    },
    {
      "date": "2025-11-25",
      "matchup": "MD vs GONZ",
      "result": "L",
      "min": 27,
      "pts": 8,
      "adjPts": 8.0,
      "pointsPlus": 83
    },
    {
      "date": "2025-11-26",
      "matchup": "MD vs ALA",
      "result": "L",
      "min": 24,
      "pts": 4,
      "adjPts": 3.0,
      "pointsPlus": 31
    },
    {
      "date": "2025-12-02",
      "matchup": "MD vs WAG",
      "result": "W",
      "min": 23,
      "pts": 9,
      "adjPts": 9.0,
      "pointsPlus": 94
    },
    {
      "date": "2025-12-06",
      "matchup": "MD @ IOWA",
      "result": "L",
      "min": 32,
      "pts": 5,
      "adjPts": 6.2,
      "pointsPlus": 64
    },
    {
      "date": "2025-12-13",
      "matchup": "MD vs MICH",
      "result": "L",
      "min": 30,
      "pts": 8,
      "adjPts": 8.2,
      "pointsPlus": 85
    },
    {
      "date": "2025-12-20",
      "matchup": "MD @ UVA",
      "result": "L",
      "min": 24,
      "pts": 10,
      "adjPts": 11.1,
      "pointsPlus": 116
    },
    {
      "date": "2025-12-28",
      "matchup": "MD vs ODU",
      "result": "W",
      "min": 27,
      "pts": 7,
      "adjPts": 7.0,
      "pointsPlus": 73
    },
    {
      "date": "2026-01-02",
      "matchup": "MD vs ORE",
      "result": "L",
      "min": 32,
      "pts": 3,
      "adjPts": 3.1,
      "pointsPlus": 32
    },
    {
      "date": "2026-01-07",
      "matchup": "MD vs IU",
      "result": "L",
      "min": 32,
      "pts": 16,
      "adjPts": 16.6,
      "pointsPlus": 173
    },
    {
      "date": "2026-01-10",
      "matchup": "MD @ UCLA",
      "result": "L",
      "min": 34,
      "pts": 17,
      "adjPts": 18.1,
      "pointsPlus": 189
    },
    {
      "date": "2026-01-13",
      "matchup": "MD @ USC",
      "result": "L",
      "min": 39,
      "pts": 6,
      "adjPts": 5.6,
      "pointsPlus": 58
    },
    {
      "date": "2026-01-18",
      "matchup": "MD vs PSU",
      "result": "W",
      "min": 24,
      "pts": 16,
      "adjPts": 14.6,
      "pointsPlus": 153
    },
    {
      "date": "2026-01-21",
      "matchup": "MD @ ILL",
      "result": "L",
      "min": 27,
      "pts": 6,
      "adjPts": 6.5,
      "pointsPlus": 67
    },
    {
      "date": "2026-01-24",
      "matchup": "MD @ MSU",
      "result": "L",
      "min": 31,
      "pts": 13,
      "adjPts": 15.1,
      "pointsPlus": 157
    },
    {
      "date": "2026-02-01",
      "matchup": "MD vs PUR",
      "result": "L",
      "min": 13,
      "pts": 0,
      "adjPts": 0.0,
      "pointsPlus": 0
    },
    {
      "date": "2026-02-05",
      "matchup": "MD vs OSU",
      "result": "L",
      "min": 28,
      "pts": 20,
      "adjPts": 19.8,
      "pointsPlus": 206
    },
    {
      "date": "2026-02-08",
      "matchup": "MD @ MINN",
      "result": "W",
      "min": 26,
      "pts": 2,
      "adjPts": 2.4,
      "pointsPlus": 25
    },
    {
      "date": "2026-02-11",
      "matchup": "MD vs IOWA",
      "result": "W",
      "min": 39,
      "pts": 12,
      "adjPts": 14.9,
      "pointsPlus": 155
    },
    {
      "date": "2026-02-15",
      "matchup": "MD @ RUTG",
      "result": "L",
      "min": 32,
      "pts": 5,
      "adjPts": 5.1,
      "pointsPlus": 53
    },
    {
      "date": "2026-02-18",
      "matchup": "MD @ NU",
      "result": "L",
      "min": 30,
      "pts": 2,
      "adjPts": 2.1,
      "pointsPlus": 22
    }
  ]
}