{
  "id": 4873145,
  "name": "Donnie Freeman",
  "team": "SYR",
  "teamName": "Syracuse Orange",
  "conference": "ACC",
  "rank": 49,
  "gp": 19,
  "ppg": 16.7,
  "adjPpg": 17.1,
  "pointsPlus": 179,
  "mpg": 30.2,
  "position": "F",
  "jersey": "1",
  "classYear": "Sophomore",
  "pointsPlusStdDev": 64.1,
  "volatilityPctile": 78,
  "gameLog": [
    {
      "date": "2025-11-03",
      "matchup": "SYR vs BING",
      "result": "W",
      "min": 25,
      "pts": 20,
      "adjPts": 20.0,
      "pointsPlus": 210
    },
    {
      "date": "2025-11-08",
      "matchup": "SYR vs DSU",
      "result": "W",
      "min": 23,
      "pts": 20,
      "adjPts": 20.0,
      "pointsPlus": 210
    },
    {
      "date": "2025-11-15",
      "matchup": "SYR vs DREX",
      "result": "W",
      "min": 28,
      "pts": 13,
      "adjPts": 13.0,
      "pointsPlus": 136
    },
    {
      "date": "2025-11-18",
      "matchup": "SYR vs MONM",
      "result": "W",
      "min": 32,
      "pts": 18,
      "adjPts": 18.0,
      "pointsPlus": 189
    },
    {
      "date": "2025-12-31",
      "matchup": "SYR vs CLEM",
      "result": "L",
      "min": 28,
      "pts": 18,
      "adjPts": 21.9,
      "pointsPlus": 230
    },
    {
      "date": "2026-01-06",
      "matchup": "SYR @ GT",
      "result": "W",
      "min": 34,
      "pts": 27,
      "adjPts": 25.8,
      "pointsPlus": 271
    },
    {
      "date": "2026-01-10",
      "matchup": "SYR @ PITT",
      "result": "W",
      "min": 30,
      "pts": 22,
      "adjPts": 24.3,
      "pointsPlus": 254
    },
    {
      "date": "2026-01-13",
      "matchup": "SYR vs FSU",
      "result": "W",
      "min": 34,
      "pts": 25,
      "adjPts": 22.9,
      "pointsPlus": 240
    },
    {
      "date": "2026-01-17",
      "matchup": "SYR @ BC",
      "result": "L",
      "min": 36,
      "pts": 19,
      "adjPts": 21.8,
      "pointsPlus": 228
    },
    {
      "date": "2026-01-21",
      "matchup": "SYR vs VT",
      "result": "L",
      "min": 32,
      "pts": 10,
      "adjPts": 9.9,
      "pointsPlus": 104
    },
    {
      "date": "2026-01-24",
      "matchup": "SYR vs MIA",
      "result": "L",
      "min": 32,
      "pts": 14,
      "adjPts": 14.5,
      "pointsPlus": 152
    },
    {
      "date": "2026-01-27",
      "matchup": "SYR @ NCSU",
      "result": "L",
      "min": 34,
      "pts": 24,
      "adjPts": 23.0,
      "pointsPlus": 241
    },
    {
      "date": "2026-01-31",
      "matchup": "SYR vs ND",
      "result": "W",
      "min": 22,
      "pts": 7,
      "adjPts": 7.2,
      "pointsPlus": 76
    },
    {
      "date": "2026-02-02",
      "matchup": "SYR @ UNC",
      "result": "L",
      "min": 35,
      "pts": 23,
      "adjPts": 24.1,
      "pointsPlus": 252
    },
    {
      "date": "2026-02-07",
      "matchup": "SYR @ UVA",
      "result": "L",
      "min": 33,
      "pts": 5,
      "adjPts": 5.5,
      "pointsPlus": 58
    },
    {
      "date": "2026-02-11",
      "matchup": "SYR vs CAL",
      "result": "W",
      "min": 34,
      "pts": 16,
      "adjPts": 16.3,
      "pointsPlus": 171
    },
    {
      "date": "2026-02-14",
      "matchup": "SYR vs SMU",
      "result": "W",
      "min": 33,
      "pts": 18,
      "adjPts": 15.8,
      "pointsPlus": 166
    },
    {
      "date": "2026-02-16",
      "matchup": "SYR @ DUKE",
      "result": "L",
      "min": 21,
      "pts": 9,
      "adjPts": 11.0,
      "pointsPlus": 115
    },
    {
      "date": "2026-02-21",
      "matchup": "SYR vs UNC",
      "result": "L",
      "min": 28,
      "pts": 9,
      "adjPts": 9.4,
      "pointsPlus": 99
    }
  ]
}