{
  "id": 5101805,
  "name": "Davion Hannah",
  "team": "ALA",
  "teamName": "Alabama Crimson Tide",
  "conference": "SEC",
  "rank": 629,
  "gp": 10,
  "ppg": 3.3,
  "adjPpg": 3.3,
  "pointsPlus": 34,
  "mpg": 12.7,
  "position": "G",
  "jersey": "4",
  "classYear": "Freshman",
  "pointsPlusStdDev": 46.0,
  "volatilityPctile": 33,
  "gameLog": [
    {
      "date": "2025-11-04",
      "matchup": "ALA vs UND",
      "result": "W",
      "min": 25,
      "pts": 9,
      "adjPts": 9.0,
      "pointsPlus": 94
    },
    {
      "date": "2025-11-08",
      "matchup": "ALA @ SJU",
      "result": "W",
      "min": 2,
      "pts": 0,
      "adjPts": 0.0,
      "pointsPlus": 0
    },
    {
      "date": "2025-11-14",
      "matchup": "ALA vs PUR",
      "result": "L",
      "min": 4,
      "pts": 0,
      "adjPts": 0.0,
      "pointsPlus": 0
    },
    {
      "date": "2025-11-20",
      "matchup": "ALA vs ILL",
      "result": "W",
      "min": 5,
      "pts": 3,
      "adjPts": 3.2,
      "pointsPlus": 33
    },
    {
      "date": "2025-11-25",
      "matchup": "ALA vs GONZ",
      "result": "L",
      "min": 4,
      "pts": 0,
      "adjPts": 0.0,
      "pointsPlus": 0
    },
    {
      "date": "2025-11-26",
      "matchup": "ALA vs UNLV",
      "result": "W",
      "min": 25,
      "pts": 0,
      "adjPts": 0.0,
      "pointsPlus": 0
    },
    {
      "date": "2025-11-27",
      "matchup": "ALA vs MD",
      "result": "W",
      "min": 16,
      "pts": 12,
      "adjPts": 11.3,
      "pointsPlus": 118
    },
    {
      "date": "2025-12-04",
      "matchup": "ALA vs CLEM",
      "result": "W",
      "min": 11,
      "pts": 0,
      "adjPts": 0.0,
      "pointsPlus": 0
    },
    {
      "date": "2025-12-07",
      "matchup": "ALA vs UTSA",
      "result": "W",
      "min": 23,
      "pts": 9,
      "adjPts": 9.0,
      "pointsPlus": 94
    },
    {
      "date": "2025-12-18",
      "matchup": "ALA vs USF",
      "result": "W",
      "min": 12,
      "pts": 0,
      "adjPts": 0.0,
      "pointsPlus": 0
    }
  ]
}