{
  "id": 5239637,
  "name": "Tajuan Simpkins",
  "team": "HALL",
  "teamName": "Seton Hall Pirates",
  "conference": "Big East",
  "rank": 267,
  "gp": 25,
  "ppg": 10.8,
  "adjPpg": 10.4,
  "pointsPlus": 109,
  "mpg": 25.8,
  "position": "G",
  "jersey": "2",
  "classYear": "Junior",
  "pointsPlusStdDev": 56.3,
  "volatilityPctile": 61,
  "gameLog": [
    {
      "date": "2025-11-04",
      "matchup": "HALL vs SPU",
      "result": "W",
      "min": 18,
      "pts": 10,
      "adjPts": 10.0,
      "pointsPlus": 105
    },
    {
      "date": "2025-11-08",
      "matchup": "HALL vs WAG",
      "result": "W",
      "min": 27,
      "pts": 15,
      "adjPts": 15.0,
      "pointsPlus": 157
    },
    {
      "date": "2025-11-11",
      "matchup": "HALL vs FAIR",
      "result": "W",
      "min": 23,
      "pts": 9,
      "adjPts": 9.0,
      "pointsPlus": 94
    },
    {
      "date": "2025-11-14",
      "matchup": "HALL vs MONM",
      "result": "W",
      "min": 31,
      "pts": 14,
      "adjPts": 14.0,
      "pointsPlus": 146
    },
    {
      "date": "2025-11-19",
      "matchup": "HALL vs NHVN",
      "result": "W",
      "min": 27,
      "pts": 18,
      "adjPts": 18.0,
      "pointsPlus": 188
    },
    {
      "date": "2025-11-24",
      "matchup": "HALL vs NCSU",
      "result": "W",
      "min": 28,
      "pts": 11,
      "adjPts": 10.4,
      "pointsPlus": 108
    },
    {
      "date": "2025-11-25",
      "matchup": "HALL vs USC",
      "result": "L",
      "min": 27,
      "pts": 8,
      "adjPts": 7.5,
      "pointsPlus": 78
    },
    {
      "date": "2025-11-26",
      "matchup": "HALL vs WSU",
      "result": "W",
      "min": 23,
      "pts": 11,
      "adjPts": 11.0,
      "pointsPlus": 115
    },
    {
      "date": "2025-12-04",
      "matchup": "HALL vs CCSU",
      "result": "W",
      "min": 23,
      "pts": 10,
      "adjPts": 10.0,
      "pointsPlus": 105
    },
    {
      "date": "2025-12-06",
      "matchup": "HALL @ KSU",
      "result": "W",
      "min": 20,
      "pts": 6,
      "adjPts": 5.2,
      "pointsPlus": 54
    },
    {
      "date": "2025-12-14",
      "matchup": "HALL vs RUTG",
      "result": "W",
      "min": 27,
      "pts": 7,
      "adjPts": 7.1,
      "pointsPlus": 74
    },
    {
      "date": "2025-12-19",
      "matchup": "HALL @ PROV",
      "result": "W",
      "min": 30,
      "pts": 22,
      "adjPts": 16.7,
      "pointsPlus": 174
    },
    {
      "date": "2025-12-24",
      "matchup": "HALL vs VILL",
      "result": "L",
      "min": 24,
      "pts": 6,
      "adjPts": 6.6,
      "pointsPlus": 69
    },
    {
      "date": "2025-12-31",
      "matchup": "HALL @ MARQ",
      "result": "W",
      "min": 22,
      "pts": 11,
      "adjPts": 10.3,
      "pointsPlus": 108
    },
    {
      "date": "2026-01-04",
      "matchup": "HALL vs CREI",
      "result": "W",
      "min": 28,
      "pts": 3,
      "adjPts": 3.0,
      "pointsPlus": 31
    },
    {
      "date": "2026-01-10",
      "matchup": "HALL @ GTWN",
      "result": "W",
      "min": 27,
      "pts": 17,
      "adjPts": 17.5,
      "pointsPlus": 183
    },
    {
      "date": "2026-01-14",
      "matchup": "HALL vs CONN",
      "result": "L",
      "min": 19,
      "pts": 2,
      "adjPts": 2.4,
      "pointsPlus": 25
    },
    {
      "date": "2026-01-17",
      "matchup": "HALL vs BUT",
      "result": "L",
      "min": 15,
      "pts": 1,
      "adjPts": 0.9,
      "pointsPlus": 10
    },
    {
      "date": "2026-01-21",
      "matchup": "HALL @ SJU",
      "result": "L",
      "min": 32,
      "pts": 14,
      "adjPts": 13.9,
      "pointsPlus": 145
    },
    {
      "date": "2026-01-24",
      "matchup": "HALL @ DEP",
      "result": "L",
      "min": 28,
      "pts": 14,
      "adjPts": 15.7,
      "pointsPlus": 164
    },
    {
      "date": "2026-01-29",
      "matchup": "HALL vs XAV",
      "result": "W",
      "min": 32,
      "pts": 27,
      "adjPts": 24.6,
      "pointsPlus": 257
    },
    {
      "date": "2026-01-31",
      "matchup": "HALL vs MARQ",
      "result": "W",
      "min": 33,
      "pts": 9,
      "adjPts": 8.4,
      "pointsPlus": 88
    },
    {
      "date": "2026-02-04",
      "matchup": "HALL @ VILL",
      "result": "L",
      "min": 24,
      "pts": 7,
      "adjPts": 7.7,
      "pointsPlus": 81
    },
    {
      "date": "2026-02-07",
      "matchup": "HALL @ CREI",
      "result": "L",
      "min": 24,
      "pts": 6,
      "adjPts": 5.9,
      "pointsPlus": 62
    },
    {
      "date": "2026-02-12",
      "matchup": "HALL vs PROV",
      "result": "W",
      "min": 32,
      "pts": 13,
      "adjPts": 9.8,
      "pointsPlus": 103
    }
  ]
}